<annotation>
    <folder>images</folder>
    <filename>videoplayback5717.jpg</filename>
    <size>
        <width>1000</width>
        <height>563</height>
        <depth>3</depth>
    </size>
    <object>
        <name>millenium_falcon</name>
        <difficult>0</difficult>
        <bndbox>
            <xmin>258</xmin>
            <ymin>312</ymin>
            <xmax>372</xmax>
            <ymax>407</ymax>
        </bndbox>
    </object>
    <object>
        <name>tiefighter</name>
        <difficult>0</difficult>
        <bndbox>
            <xmin>478</xmin>
            <ymin>75</ymin>
            <xmax>844</xmax>
            <ymax>470</ymax>
        </bndbox>
    </object>
</annotation>